async_pychasing/__init__.py
async_pychasing/_client.py
async_pychasing/_session.py
async_pychasing-0.0.1.dist-info/LICENSE
async_pychasing-0.0.1.dist-info/METADATA
async_pychasing-0.0.1.dist-info/WHEEL
async_pychasing-0.0.1.dist-info/top_level.txt
async_pychasing-0.0.1.dist-info/RECORD
