Metadata-Version: 2.1
Name: async-pychasing
Version: 0.0.1
Summary: An asynchronous version of [pychasing](https://pypi.org/project/pychasing/) (a wrapper for the https://ballchasing.com API)
Author-email: "Tanner B. Corcoran" <tannerbcorcoran@gmail.com>
Project-URL: Homepage, https://github.com/tanrbobanr/async-pychasing
Classifier: Programming Language :: Python :: 3
Classifier: License :: OSI Approved :: MIT License
Classifier: Operating System :: OS Independent
Requires-Python: >=3.7
License-File: LICENSE
Requires-Dist: aiohttp (>=3.5.0)
Requires-Dist: http-prep (>=0.0.6)
Requires-Dist: prepr (>=0.0.6)
Requires-Dist: pychasing (>=0.1.3)
